README.rst
setup.py
celerybeat_mongo.egg-info/PKG-INFO
celerybeat_mongo.egg-info/SOURCES.txt
celerybeat_mongo.egg-info/dependency_links.txt
celerybeat_mongo.egg-info/requires.txt
celerybeat_mongo.egg-info/top_level.txt
celerybeatmongo/__init__.py
celerybeatmongo/models.py
celerybeatmongo/schedulers.py