Metadata-Version: 1.0
Name: celerybeat-mongo
Version: 0.0.8
Summary: A Celery Beat Scheduler that uses MongoDB to store both schedule definitions and status information
Home-page: UNKNOWN
Author: Zakir Durumeric
Author-email: zakird@gmail.com
License: Apache License, Version 2.0
Keywords: python celery beat mongo
Platform: UNKNOWN
